datasist/__init__.py
datasist/feature_engineering.py
datasist/model.py
datasist/nlp.py
datasist/project.py
datasist/structdata.py
datasist/timeseries.py
datasist/visualizations.py
datasist/tests/__init__.py
datasist/tests/test_feature_engineering.py
datasist/tests/test_model.py
datasist/tests/test_nlp.py
datasist/tests/test_project.py
datasist/tests/test_timeseries.py
datasist-1.5.3.dist-info/LICENCE.txt
datasist-1.5.3.dist-info/METADATA
datasist-1.5.3.dist-info/WHEEL
datasist-1.5.3.dist-info/entry_points.txt
datasist-1.5.3.dist-info/top_level.txt
datasist-1.5.3.dist-info/RECORD
