Metadata-Version: 2.1
Name: datasist
Version: 1.5.3
Summary: A Python library for easy data analysis, visualization, exploration and modeling
Home-page: https://github.com/risenW/datasist
Author: Rising Odegua
Author-email: risingodegua@gmail.com
License: MIT
Download-URL: https://github.com/risenW/datasist/archive/v1.5.3.tar.gz
Keywords: Data Analysis,Feature Engineering,Visualization,project management,modeling,machine learning
Platform: UNKNOWN
Classifier: Development Status :: 5 - Production/Stable
Classifier: Intended Audience :: Developers
Classifier: Topic :: Software Development :: Build Tools
Classifier: License :: OSI Approved :: MIT License
Classifier: Programming Language :: Python :: 3.7
Classifier: Programming Language :: Python :: 3.5
Classifier: Programming Language :: Python :: 3.6
Requires-Dist: pandas
Requires-Dist: matplotlib
Requires-Dist: seaborn
Requires-Dist: numpy
Requires-Dist: jupyter
Requires-Dist: scikit-learn
Requires-Dist: nltk
Requires-Dist: Joblib
